bezzanlabs/treemachine/__init__.py
bezzanlabs/treemachine/auto_trees/__init__.py
bezzanlabs/treemachine/auto_trees/base.py
bezzanlabs/treemachine/auto_trees/classifier_cv.py
bezzanlabs/treemachine/auto_trees/defaults.py
bezzanlabs/treemachine/auto_trees/metrics.py
bezzanlabs/treemachine/auto_trees/optimizer_base.py
bezzanlabs/treemachine/auto_trees/regression_cv.py
bezzanlabs/treemachine/auto_trees/transforms.py
bezzanlabs/treemachine/auto_trees/types.py
bezzanlabs.treemachine-1.2.3.dist-info/LICENSE
bezzanlabs.treemachine-1.2.3.dist-info/METADATA
bezzanlabs.treemachine-1.2.3.dist-info/WHEEL
bezzanlabs.treemachine-1.2.3.dist-info/top_level.txt
bezzanlabs.treemachine-1.2.3.dist-info/RECORD
