Metadata-Version: 2.1
Name: bezzanlabs.treemachine
Version: 1.2.3
Summary: An AutoML companion to fit tree models easily
Author-email: Vitor Bezzan <vitor@bezzan.com>
Project-URL: Homepage, https://github.com/vitorbezzan/tree_machine
Project-URL: Bug Tracker, https://github.com/vitorbezzan/tree_machine
Requires-Python: >=3.11
License-File: LICENSE
Requires-Dist: numpy <2.0.0,>1.0.0
Requires-Dist: pandas >=2.2.1
Requires-Dist: scikit-learn ~=1.4
Requires-Dist: xgboost ~=2.0
Requires-Dist: imbalanced-learn ~=0.12
Requires-Dist: shap ==0.45
Requires-Dist: optuna ~=3.6.1
Requires-Dist: optuna-integration ==3.6.0
Requires-Dist: pydantic ~=2.7.4
Provides-Extra: dev
Requires-Dist: pre-commit ==3.5.0 ; extra == 'dev'
Requires-Dist: mypy ==1.6.0 ; extra == 'dev'
Requires-Dist: pylint ==3.0.1 ; extra == 'dev'
Requires-Dist: pytest ==7.3.1 ; extra == 'dev'
Requires-Dist: pytest-mock ; extra == 'dev'
Requires-Dist: pytest-cov ; extra == 'dev'
Requires-Dist: safety ==2.3.5 ; extra == 'dev'
Requires-Dist: sphinx-autodoc-typehints ==1.24.1 ; extra == 'dev'
Requires-Dist: nbsphinx ==0.9.3 ; extra == 'dev'
Requires-Dist: sphinx ==7.2.6 ; extra == 'dev'
Requires-Dist: sphinx-copybutton ==0.5.2 ; extra == 'dev'
Requires-Dist: sphinx-rtd-theme ==1.3.0 ; extra == 'dev'
Requires-Dist: recommonmark ==0.7.1 ; extra == 'dev'
Requires-Dist: isort ==5.12.0 ; extra == 'dev'
Requires-Dist: pandas-stubs ==2.1.1.230928 ; extra == 'dev'
